{
  "project_info": {
    "project_number": "592726415134",
    "project_id": "shoflakklba",
    "storage_bucket": "shoflakklba.firebasestorage.app"
  },
  "client": [
    {
      "client_info": {
        "mobilesdk_app_id": "1:592726415134:android:fe690694e3a33c4aee1b0f",
        "android_client_info": {
          "package_name": "com.shoflakklba.app"
        }
      },
      "oauth_client": [],
      "api_key": [
        {
          "current_key": "AIzaSyBVfRHOXN3Kmkoo2U0Q7o6Idbpmz2U6rDg"
        }
      ],
      "services": {
        "appinvite_service": {
          "other_platform_oauth_client": []
        }
      }
    }
  ],
  "configuration_version": "1"
}
